grevling/__init__.py
grevling/__main__.py
grevling/api.py
grevling/capture.py
grevling/context.py
grevling/filemap.py
grevling/grevling.gold
grevling/parameters.py
grevling/plotting.py
grevling/render.py
grevling/schema/__init__.py
grevling/schema/raw.py
grevling/schema/refined.py
grevling/script.py
grevling/typing.py
grevling/util.py
grevling/workflow/__init__.py
grevling/workflow/local.py
grevling-2.1.3.dist-info/LICENSE
grevling-2.1.3.dist-info/METADATA
grevling-2.1.3.dist-info/WHEEL
grevling-2.1.3.dist-info/entry_points.txt
grevling-2.1.3.dist-info/RECORD
