Metadata-Version: 2.1
Name: grevling
Version: 2.1.3
Summary: A batch runner tool
License: AGPL3
Author: Eivind Fonn
Author-email: eivind.fonn@sintef.no
Requires-Python: >=3.9,<4.0
Classifier: License :: Other/Proprietary License
Classifier: Programming Language :: Python :: 3
Classifier: Programming Language :: Python :: 3.9
Classifier: Programming Language :: Python :: 3.10
Classifier: Programming Language :: Python :: 3.11
Classifier: Programming Language :: Python :: 3.12
Classifier: Programming Language :: Python :: 3.13
Requires-Dist: Mako (>=1.2.2,<2.0.0)
Requires-Dist: PyYAML (>=6.0.1,<7.0.0)
Requires-Dist: asteval (>=0.9.31,<0.10.0)
Requires-Dist: bidict (>=0.22.1,<0.23.0)
Requires-Dist: click (>=8.1.7,<9.0.0)
Requires-Dist: fasteners (>=0.19,<0.20)
Requires-Dist: goldpy (>=2.1,<3.0)
Requires-Dist: numpy (>=1.24,<2.0)
Requires-Dist: pandas (>=2.0,<3.0)
Requires-Dist: pyarrow (>=14.0.1,<15.0.0)
Requires-Dist: pydantic (>=2,<3)
Requires-Dist: rich (>=13.6.0,<14.0.0)
Requires-Dist: typing-extensions (==4.11.0)
